waf_run/__init__.py
waf_run-0.0.1.dist-info/METADATA
waf_run-0.0.1.dist-info/WHEEL
waf_run-0.0.1.dist-info/licenses/LICENSE
waf_run-0.0.1.dist-info/RECORD
