Metadata-Version: 2.1
Name: waf_run
Version: 0.0.1
Summary: A dumb package
Author-email: Example Author <author@example.com>
License-File: LICENSE
Classifier: License :: OSI Approved :: MIT License
Classifier: Operating System :: OS Independent
Classifier: Programming Language :: Python :: 2
Requires-Python: >=2.3
